juniper/__init__.py
juniper/actions.py
juniper/cli.py
juniper/constants.py
juniper/io.py
juniper/manifest.py
juniper/artifacts/build_layer.sh
juniper/artifacts/compose-template.yml
juniper/artifacts/package.sh
juniper_aidentified-0.8.1.dist-info/AUTHORS
juniper_aidentified-0.8.1.dist-info/LICENSE
juniper_aidentified-0.8.1.dist-info/METADATA
juniper_aidentified-0.8.1.dist-info/WHEEL
juniper_aidentified-0.8.1.dist-info/entry_points.txt
juniper_aidentified-0.8.1.dist-info/top_level.txt
juniper_aidentified-0.8.1.dist-info/RECORD
