Metadata-Version: 2.1
Name: juniper-aidentified
Version: 0.8.1
Summary: Tool to streamline the build of python lambda functions. (fork of juniper)
Author: Aidentified LLC
Author-email: dgilman@aidentified.com
License: Apache Software License
Project-URL: Code, https://github.com/dgilmanAIDENTIFIED/juniper
Classifier: Environment :: Web Environment
Classifier: Intended Audience :: Developers
Classifier: License :: OSI Approved :: Apache Software License
Classifier: Operating System :: OS Independent
Classifier: Programming Language :: Python
Classifier: Programming Language :: Python :: 3.9
Classifier: Programming Language :: Python :: 3.10
Classifier: Programming Language :: Python :: 3.11
Classifier: Topic :: Software Development :: Libraries :: Python Modules
Classifier: Topic :: Software Development :: Build Tools
Requires-Python: >=3.9
License-File: LICENSE
License-File: AUTHORS
Requires-Dist: click >=8.0
Requires-Dist: click-log
Requires-Dist: PyYAML >=6.0
Requires-Dist: Jinja2 >=3.0
